{
  "health_001": "أن تكون في إجازة طبية",
  "health_002": "للشفاء / للعالج للخضوع",
  "health_003": "الطين حمامات أخذ",
  "health_004": "شهادة طبية / تقرير مرضي",
  "health_005": "لقياس النبض/ضغط الدم",
  "health_006": "جراحة",
  "health_007": "المستشفى صالة",
  "health_008": "للحفاظ على النظام / احترام النظام",
  "health_009": "للحمية خبز",
  "health_010": "السعال الغزير",
  "health_011": "الدم ضغط انخفاض / فرط",
  "health_012": "العالج تلقي",
  "health_013": "الم حاد",
  "health_014": "سيارة إسعاف، إسعافات أولية",
  "health_015": "صحية بوعكة يشعر",
  "health_016": "لفقدان الوعي",
  "health_017": "استشارة الطبيب",
  "health_018": "وقائية",
  "health_019": "قسم العناية المركزة/ واإلنعاش",
  "health_020": "العالج نجاح",
  "health_021": "الوقاية من األمراض المعدية",
  "health_022": "مستشفى الاطفال/ مكتب طبيب الأطفال للاستشارة"
}
