{
  "health_001": "Бути в лікарняній відпустці / Взяти лікарняний",
  "health_002": "Дотримуватися курсу лікування",
  "health_003": "Приймати грязьові ванни",
  "health_004": "Медична довідка",
  "health_005": "Перевірити пульс",
  "health_006": "Хірургічне втручання",
  "health_007": "Лікарняна палата",
  "health_008": "Дотримуватися режиму",
  "health_009": "Дієтичний хліб",
  "health_010": "Сильний кашель",
  "health_011": "Гіпертонія",
  "health_012": "Приймати ліки",
  "health_013": "Коліки",
  "health_014": "Швидка",
  "health_015": "Йому / їй стало погано",
  "health_016": "Втратити свідомість",
  "health_017": "Лікар-консультант",
  "health_018": "Профілакторій",
  "health_019": "Відділ реанімації",
  "health_020": "Лікування подіяло / дало результати",
  "health_021": "Профілактика інфекційних захворювань",
  "health_022": "Кабінет педіатрії для консультацій педіатричний /дитяча клініка"
}
